{"2019":{"country_or_territory":"Congo Republic of","population":"5381000","peak_pubs":"8808","ratio_1_publisher_to":"651","av_pubs":"8260","inc_over":"10","no_bptzd":"732","av_pio_pubs":"970","no_of_congs":"98","memorial_attendance":"34754"},"2020":{"country_or_territory":"Congo Republic of","population":"5518000","peak_pubs":"9192","ratio_1_publisher_to":"667","av_pubs":"8277","inc_over":"","no_bptzd":"368","av_pio_pubs":"1096","no_of_congs":"117","memorial_attendance":"21820"},"2021":{"country_or_territory":"Congo Republic of","population":"5657000","peak_pubs":"8358","ratio_1_publisher_to":"703","av_pubs":"8045","inc_over":"-3","no_bptzd":"357","av_pio_pubs":"1138","no_of_congs":"116","av_bible_studies":"11100","memorial_attendance":"25022"},"2022":{"country_or_territory":"Congo Republic of","population":"5798000","peak_pubs":"8556","ratio_1_publisher_to":"707","av_pubs":"8200","inc_over":"2","no_bptzd":"194","av_pio_pubs":"1250","no_of_congs":"116","av_bible_studies":"12653","memorial_attendance":"25093"}}