{"2019":{"country_or_territory":"Japan","population":"126860000","peak_pubs":"212651","ratio_1_publisher_to":"597","av_pubs":"212438","inc_over":"","no_bptzd":"2118","av_pio_pubs":"66100","no_of_congs":"2991","memorial_attendance":"291206"},"2020":{"country_or_territory":"Japan","population":"126476000","peak_pubs":"212683","ratio_1_publisher_to":"598","av_pubs":"211494","inc_over":"","no_bptzd":"1910","av_pio_pubs":"66206","no_of_congs":"2964","memorial_attendance":"273856"},"2021":{"country_or_territory":"Japan","population":"126051000","peak_pubs":"213451","ratio_1_publisher_to":"592","av_pubs":"212911","inc_over":"1","no_bptzd":"1621","av_pio_pubs":"66947","no_of_congs":"2959","av_bible_studies":"71178","memorial_attendance":"321158"},"2022":{"country_or_territory":"Japan","population":"125194000","peak_pubs":"214359","ratio_1_publisher_to":"585","av_pubs":"213828","inc_over":"","no_bptzd":"1858","av_pio_pubs":"69606","no_of_congs":"2893","av_bible_studies":"74891","memorial_attendance":"310692"}}