{"2019":{"country_or_territory":"Mozambique","population":"30366000","peak_pubs":"67758","ratio_1_publisher_to":"463","av_pubs":"65593","inc_over":"9","no_bptzd":"7162","av_pio_pubs":"6114","no_of_congs":"1315","memorial_attendance":"334110"},"2020":{"country_or_territory":"Mozambique","population":"30067000","peak_pubs":"68996","ratio_1_publisher_to":"454","av_pubs":"66171","inc_over":"1","no_bptzd":"2763","av_pio_pubs":"6688","no_of_congs":"1297","memorial_attendance":"238288"},"2021":{"country_or_territory":"Mozambique","population":"30832000","peak_pubs":"89946","ratio_1_publisher_to":"446","av_pubs":"69106","inc_over":"4","no_bptzd":"5179","av_pio_pubs":"6729","no_of_congs":"1313","av_bible_studies":"80890","memorial_attendance":"269122"},"2022":{"country_or_territory":"Mozambique","population":"31616000","peak_pubs":"81719","ratio_1_publisher_to":"427","av_pubs":"73993","inc_over":"7","no_bptzd":"2728","av_pio_pubs":"6854","no_of_congs":"1551","av_bible_studies":"87042","memorial_attendance":"286696"}}