{"2019":{"country_or_territory":"Nepal","population":"28609000","peak_pubs":"2659","ratio_1_publisher_to":"10890","av_pubs":"2627","inc_over":"1","no_bptzd":"136","av_pio_pubs":"890","no_of_congs":"42","memorial_attendance":"6995"},"2020":{"country_or_territory":"Nepal","population":"29137000","peak_pubs":"2699","ratio_1_publisher_to":"10966","av_pubs":"2657","inc_over":"1","no_bptzd":"221","av_pio_pubs":"838","no_of_congs":"43","memorial_attendance":"6524"},"2021":{"country_or_territory":"Nepal","population":"29675000","peak_pubs":"2809","ratio_1_publisher_to":"10717","av_pubs":"2769","inc_over":"4","no_bptzd":"157","av_pio_pubs":"824","no_of_congs":"43","av_bible_studies":"3007","memorial_attendance":"9378"},"2022":{"country_or_territory":"Nepal","population":"29192000","peak_pubs":"2823","ratio_1_publisher_to":"10415","av_pubs":"2803","inc_over":"1","no_bptzd":"96","av_pio_pubs":"869","no_of_congs":"43","av_bible_studies":"2735","memorial_attendance":"7529"}}